{
  "id": "4034013",
  "game": "sr",
  "entityType": "enemy",
  "name": "末日歧途的盗火者",
  "description": "伴随黑潮而来、狩猎泰坦火种的无名剑士，无人知晓其真身。<br>身负不可思议的力量，剑技也近乎无懈可击。疯狂与执着交织于它的锋刃，神悟树庭与哀丽秘榭皆毁于其手。",
  "stats": {
    "HP": 100.0,
    "ATK": 18.0,
    "DEF": 1.0,
    "SPD": 132.0,
    "Stance": 40.0
  },
  "weakness": [
    "Phys",
    "Ice",
    "Elec",
    "Quantum"
  ],
  "resistance": {
    "Fire": 0.4,
    "Wind": 0.4,
    "Imaginary": 0.4
  },
  "statusResist": 0.3,
  "icon": "mostericon/Monster_4034010.png",
  "figure": "monsterfigure/Monster_4034010.png",
  "camp": {
    "id": "0",
    "name": null
  },
  "analysis": {
    "_id": 403401304,
    "Notes": [
      {
        "DescList": [
          "• 正常状态下，首领攻击会@召唤分身#，其被消灭使首领损失 @25%# 韧性",
          "• 首领第二层韧性@被锁定#（免疫削韧），失去第一层韧性时，立即行动，并进入@【镣铐崩解】#状态：交替进行【召唤分身】和【终结技】，攻击力提升 @25%# ，速度提升 @25%#"
        ]
      },
      {
        "Title": "召唤分身",
        "DescList": [
          "• 使自身@不可选中#，召唤 @4# 个分身，分身被消灭后被重新召唤，且使首领损失 @10.5%# 韧性和 @0.3%# 生命值",
          "• 召唤两个常规分身后，下一个被替换为特殊分身：仅具有原血量 @30%# 的血量，被击杀后不削减首领韧性，但击杀者获得一个@可叠加额外回合#，且造成的伤害提升 @50%#"
        ]
      }
    ]
  },
  "source": {
    "files": [
      "data/CH/Monster_1.js",
      "data/CH/Monster_2.js"
    ]
  }
}
