{
  "id": "8015011",
  "game": "sr",
  "entityType": "enemy",
  "name": "末日兽",
  "description": "「反物质军团」以黄昏古兽的残片为基「战争熔炉」的万骸哀怨为引所铸炼而成「末日兽」之一。怨灵的痴缠化作有形之手，旧日的灾影凝为掩映诸天之尾。「末日兽」拘禁了未释然亦未死灭的众生意志。或嗔怒，或忧恸，或妄喜——迷相既露，诸邪肆动。「末日兽」的核心为一颗暗物质驱动的引擎。",
  "stats": {
    "HP": 7.5,
    "ATK": 18.0,
    "DEF": 1.0,
    "SPD": 0.0,
    "Stance": 0.0
  },
  "weakness": [
    "Phys",
    "Fire",
    "Ice",
    "Wind"
  ],
  "resistance": {},
  "statusResist": 1.0,
  "icon": "mostericon/Monster_8015010.png",
  "figure": "monsterfigure/Monster_8015010.png",
  "camp": {
    "id": "6",
    "name": "反物质军团"
  },
  "analysis": null,
  "source": {
    "files": [
      "data/CH/Monster_1.js",
      "data/CH/Monster_2.js"
    ]
  }
}
